MANIFEST.in
README.md
requirements.txt
setup.cfg
setup.py
versioneer.py
botcity/plugins/googlecalendar/__init__.py
botcity/plugins/googlecalendar/_version.py
botcity/plugins/googlecalendar/plugin.py
botcity_googlecalendar_plugin.egg-info/PKG-INFO
botcity_googlecalendar_plugin.egg-info/SOURCES.txt
botcity_googlecalendar_plugin.egg-info/dependency_links.txt
botcity_googlecalendar_plugin.egg-info/requires.txt
botcity_googlecalendar_plugin.egg-info/top_level.txt
tests/test_import.py
tests/test_plugin.py